MSpeechPy/CONSTANTS.py
MSpeechPy/__init__.py
MSpeechPy/__version__.py
MSpeechPy/client.py
MSpeechPy/exeptions.py
MSpeechPy/ssml_builder.py
MSpeechPy/_builds/__init__.py
MSpeechPy/_builds/api.py
MSpeechPy/_builds/speech.py
MSpeechPy/_builds/voices.py
MSpeechPy-0.2.2.dist-info/METADATA
MSpeechPy-0.2.2.dist-info/WHEEL
MSpeechPy-0.2.2.dist-info/top_level.txt
MSpeechPy-0.2.2.dist-info/RECORD
