Metadata-Version: 2.1
Name: MSpeechPy
Version: 0.2.2
Summary: Converter texto para voz
Author: PauloCesar-dev404
Author-email: paulocesar0073dev404@gmail.com
License: MIT
Project-URL: GitHub, https://github.com/PauloCesar-dev404/MSpeechPy
Project-URL: Bugs/Melhorias, https://github.com/PauloCesar-dev404/MSpeechPy/issues
Project-URL: Documentação, https://github.com/PauloCesar-dev404/MSpeechPy/wiki
Keywords: tts,MSpeechPy,converter texto para voz,text for voice,azure tts
Platform: any
Requires-Dist: azure-identity
Requires-Dist: requests
